nonebot_plugin_abbrreply/__init__.py
nonebot_plugin_abbrreply-1.1.3.dist-info/METADATA
nonebot_plugin_abbrreply-1.1.3.dist-info/WHEEL
nonebot_plugin_abbrreply-1.1.3.dist-info/top_level.txt
nonebot_plugin_abbrreply-1.1.3.dist-info/RECORD
