Metadata-Version: 2.1
Name: nonebot-plugin-abbrreply
Version: 1.1.3
Summary: 缩写查询器
Home-page: https://github.com/anlen123/nonebot_plugin_abbrreply
Author: anlen123
Author-email: 1761512493@qq.com
Maintainer: anlen123
Maintainer-email: 1761512493@qq.com
License: UNKNOWN
Platform: all
